{
  "АКПП": "automatic",
  "акпп": "automatic",
  "автомат": "automatic",
  "автоматическая": "automatic",
  "AT": "automatic",
  "A/T": "automatic",
  "automatic": "automatic",
  "МКПП": "manual",
  "мкпп": "manual",
  "механика": "manual",
  "механическая": "manual",
  "MT": "manual",
  "M/T": "manual",
  "manual": "manual",
  "вариатор": "cvt",
  "Вариатор": "cvt",
  "CVT": "cvt",
  "cvt": "cvt",
  "робот": "robot",
  "роботизированная": "robot",
  "роботизированная коробка": "robot",
  "DCT": "robot",
  "dct": "robot"
}